gcp_pubsub_dao/__init__.py
gcp_pubsub_dao/async_pubsub_publisher_dao.py
gcp_pubsub_dao/async_pubsub_subscriber_dao.py
gcp_pubsub_dao/entities.py
gcp_pubsub_dao/pubsub_publisher_dao.py
gcp_pubsub_dao/pubsub_subscriber_dao.py
gcp_pubsub_dao/worker_pool.py
gcp_pubsub_dao-0.4.0.dist-info/METADATA
gcp_pubsub_dao-0.4.0.dist-info/WHEEL
gcp_pubsub_dao-0.4.0.dist-info/RECORD
