Metadata-Version: 2.1
Name: gcp-pubsub-dao
Version: 0.4.0
Summary: DAO for GCP PubSub service.
Author: Raman Shakun
Author-email: shakunroman@gmail.com
Requires-Python: >=3.11,<4.0
Classifier: Programming Language :: Python :: 3
Classifier: Programming Language :: Python :: 3.11
Requires-Dist: google-cloud-pubsub (>=2.19.0,<3.0.0)
